versionator_mcp/__init__.py
versionator_mcp/app.py
versionator_mcp/config.py
versionator_mcp/main.py
versionator_mcp/models.py
versionator_mcp/core/__init__.py
versionator_mcp/core/base_registry.py
versionator_mcp/core/http_client.py
versionator_mcp/core/registry_factory.py
versionator_mcp/registries/__init__.py
versionator_mcp/registries/bioconda.py
versionator_mcp/registries/composer.py
versionator_mcp/registries/cpan.py
versionator_mcp/registries/cran.py
versionator_mcp/registries/crates.py
versionator_mcp/registries/dockerhub.py
versionator_mcp/registries/go.py
versionator_mcp/registries/hex.py
versionator_mcp/registries/homebrew.py
versionator_mcp/registries/maven.py
versionator_mcp/registries/nextflow.py
versionator_mcp/registries/nfcore.py
versionator_mcp/registries/npm.py
versionator_mcp/registries/nuget.py
versionator_mcp/registries/pypi.py
versionator_mcp/registries/rubygems.py
versionator_mcp/registries/swift.py
versionator_mcp/registries/terraform.py
versionator_mcp/tools/__init__.py
versionator_mcp/tools/registry_tools.py
versionator_mcp-1.3.1.dist-info/licenses/LICENSE
versionator_mcp-1.3.1.dist-info/METADATA
versionator_mcp-1.3.1.dist-info/WHEEL
versionator_mcp-1.3.1.dist-info/entry_points.txt
versionator_mcp-1.3.1.dist-info/top_level.txt
versionator_mcp-1.3.1.dist-info/RECORD
