Metadata-Version: 2.4
Name: versionator-mcp
Version: 1.3.1
Summary: An MCP server that queries package registries across 19 different ecosystems for latest package versions
Author-email: Alaina Hardie <alainahardie@gmail.com>
License: MIT
Project-URL: Homepage, https://github.com/trianglegrrl/versionator-mcp
Project-URL: Repository, https://github.com/trianglegrrl/versionator-mcp.git
Project-URL: Issues, https://github.com/trianglegrrl/versionator-mcp/issues
Keywords: mcp,model-context-protocol,package-manager,npm,pypi,rubygems,hex
Classifier: Development Status :: 5 - Production/Stable
Classifier: Intended Audience :: Developers
Classifier: License :: OSI Approved :: MIT License
Classifier: Operating System :: OS Independent
Classifier: Programming Language :: Python :: 3
Classifier: Programming Language :: Python :: 3.10
Classifier: Programming Language :: Python :: 3.11
Classifier: Programming Language :: Python :: 3.12
Classifier: Topic :: Software Development :: Libraries :: Python Modules
Classifier: Topic :: System :: Software Distribution
Requires-Python: >=3.10
License-File: LICENSE
Requires-Dist: fastmcp>=2.11.3
Requires-Dist: aiohttp>=3.8.0
Requires-Dist: pydantic>=2.0.0
Provides-Extra: dev
Requires-Dist: pytest>=8.3.3; extra == "dev"
Requires-Dist: pytest-asyncio>=0.23.0; extra == "dev"
Requires-Dist: pytest-cov>=5.0.0; extra == "dev"
Requires-Dist: black>=24.0.0; extra == "dev"
Requires-Dist: isort>=5.12.0; extra == "dev"
Requires-Dist: mypy>=1.8.0; extra == "dev"
Requires-Dist: pre-commit>=3.8.0; extra == "dev"
Dynamic: license-file
